<?xml version="1.0" encoding="utf-8"?>
<lfm status="ok">
<track>
    <id>74899839</id>
    <name>La Tina</name>
            <mbid>2fb62987-f0bf-44fe-8f87-3756e23e8eab</mbid>
            <url>http://www.last.fm/music/Ximena+Sari%C3%B1ana/_/La+Tina</url>
    <duration>235000</duration>
    <streamable fulltrack="0">1</streamable>    
        <listeners>28802</listeners>
    <playcount>105303</playcount>
        <artist>
        <name>Ximena Sariñana</name>
                <mbid>c757e9ae-b246-4a55-8b43-726a64f4012a</mbid>
                    <url>http://www.last.fm/music/Ximena+Sari%C3%B1ana</url>
    </artist>
        <album position="6">
        <artist>Ximena Sariñana</artist>
        <title>Ximena</title>
                <mbid></mbid>
                    <url>http://www.last.fm/music/Ximena+Sari%C3%B1ana/Ximena</url>        
        <image size="small">http://userserve-ak.last.fm/serve/64s/7156393.jpg</image>
        <image size="medium">http://userserve-ak.last.fm/serve/126/7156393.jpg</image>
        <image size="large">http://userserve-ak.last.fm/serve/174s/7156393.jpg</image>
        <image size="extralarge">http://userserve-ak.last.fm/serve/300x300/7156393.jpg</image>
    </album>
        <toptags>
        <tag>
	  <name>female vocalists</name>
	  <url>http://www.last.fm/tag/female%20vocalists</url>
	</tag>
        <tag>
	  <name>pop</name>
	  <url>http://www.last.fm/tag/pop</url>
	</tag>
        <tag>
	  <name>ximena</name>
	  <url>http://www.last.fm/tag/ximena</url>
	</tag>
        <tag>
	  <name>sexy</name>
	  <url>http://www.last.fm/tag/sexy</url>
	</tag>
        <tag>
	  <name>tranquil</name>
	  <url>http://www.last.fm/tag/tranquil</url>
	</tag>
      </toptags>
          <wiki>
        <published>Tue, 3 Mar 2009 21:01:48 +0000</published>
        <summary><![CDATA[Mexican pop artist and actress. She sings in diverse styles. Jazz, Afro, Latin. Beautiful voice and style.]]></summary>
        <content><![CDATA[Mexican pop artist and actress. She sings in diverse styles. Jazz, Afro, Latin. Beautiful voice and style.
        
User-contributed text is available under the Creative Commons By-SA License and may also be available under the GNU FDL.]]></content>
      </wiki>
    </track></lfm>
